setup.py
src/zope/__init__.py
src/zope.app.dublincore.egg-info/PKG-INFO
src/zope.app.dublincore.egg-info/SOURCES.txt
src/zope.app.dublincore.egg-info/dependency_links.txt
src/zope.app.dublincore.egg-info/namespace_packages.txt
src/zope.app.dublincore.egg-info/not-zip-safe
src/zope.app.dublincore.egg-info/requires.txt
src/zope.app.dublincore.egg-info/top_level.txt
src/zope/app/__init__.py
src/zope/app/dublincore/__init__.py
src/zope/app/dublincore/annotatableadapter.py
src/zope/app/dublincore/creatorannotator.py
src/zope/app/dublincore/dcsv.py
src/zope/app/dublincore/dcterms.py
src/zope/app/dublincore/interfaces.py
src/zope/app/dublincore/timeannotators.py
src/zope/app/dublincore/xmlmetadata.py
src/zope/app/dublincore/zopedublincore.py