Metadata-Version: 1.0
Name: zope.app.dublincore
Version: 3.4.0
Summary: A deprecated backwards compatibility package
Home-page: http://pypi.python.org/pypi/zope.app.dublincore
Author: Zope Corporation and Contributors
Author-email: zope3-dev@zope.org
License: ZPL 2.1
Platform: UNKNOWN
